fastT5/__init__.py
fastT5/model_testing_tools.py
fastT5/onnx_exporter.py
fastT5/onnx_models.py
fastT5/onnx_models_structure.py
fastT5/ort_settings.py
tests/__init__.py
tests/models_test.py
fastt5-0.0.1.dist-info/LICENSE
fastt5-0.0.1.dist-info/METADATA
fastt5-0.0.1.dist-info/WHEEL
fastt5-0.0.1.dist-info/top_level.txt
fastt5-0.0.1.dist-info/RECORD
