Metadata-Version: 2.1
Name: fastt5
Version: 0.0.1
Summary: boost inference speed of T5 models by 5x & reduce the model size by 3x using fastT5.
Home-page: https://github.com/Ki6an/fastT5
Author: Kiran R
Author-email: kiranr8k@gmail.com
License: apache-2.0
Project-URL: Repo, https://github.com/Ki6an/fastT5
Project-URL: Bug Tracker, https://github.com/Ki6an/fastT5/issues
Keywords: T5,ONNX,onnxruntime,NLP,transformer,quantization,generate text,summarization,translation,q&a,qg,machine learning,inference,fast inference
Platform: UNKNOWN
Classifier: Development Status :: 3 - Alpha
Classifier: Intended Audience :: Developers
Classifier: Topic :: Scientific/Engineering :: Artificial Intelligence
Classifier: License :: OSI Approved :: Apache Software License
Classifier: Programming Language :: Python :: 3
Classifier: Programming Language :: Python :: 3.5
Classifier: Programming Language :: Python :: 3.6
Classifier: Programming Language :: Python :: 3.7
Classifier: Programming Language :: Python :: 3.8
Requires-Python: >=3.5
Requires-Dist: onnxruntime (>=1.6.0)
Requires-Dist: torch (==1.7.0)
Requires-Dist: onnx (==1.8.1)
Requires-Dist: onnxruntime (==1.7.0)
Requires-Dist: transformers (==4.2.2)
Requires-Dist: progress (==1.5)
Requires-Dist: numpy (==1.15.2)
Requires-Dist: tqdm (==4.48.2)
Requires-Dist: sentencepiece
